doublespike/__init__.py
doublespike/calibrate.py
doublespike/cocktail.py
doublespike/errors.py
doublespike/inversion.py
doublespike/isodata.py
doublespike/monte.py
doublespike/optimal.py
doublespike/plotting.py
doublespike/data/maininput.csv
doublespike-1.0.1.dist-info/LICENSE
doublespike-1.0.1.dist-info/METADATA
doublespike-1.0.1.dist-info/WHEEL
doublespike-1.0.1.dist-info/top_level.txt
doublespike-1.0.1.dist-info/RECORD
