Metadata-Version: 2.1
Name: doublespike
Version: 1.0.1
Summary: The double spike toolbox
Author-email: "John F. Rudge" <jfr23@cam.ac.uk>
Project-URL: Homepage, https://github.com/johnrudge/pyspike
Project-URL: Bug Tracker, https://github.com/johnrudge/pyspike/issues
Classifier: Programming Language :: Python :: 3
Classifier: License :: OSI Approved :: MIT License
Classifier: Operating System :: OS Independent
Requires-Python: >=3.9
License-File: LICENSE
Requires-Dist: numpy
Requires-Dist: scipy
Requires-Dist: matplotlib
